kio/__init__.py
kio/_utils.py
kio/_version.py
kio/index.py
kio/py.typed
kio/records/__init__.py
kio/records/readers.py
kio/records/schema.py
kio/records/writers.py
kio/schema/__init__.py
kio/schema/errors.py
kio/schema/index.py
kio/schema/types.py
kio/schema/add_offsets_to_txn/__init__.py
kio/schema/add_offsets_to_txn/v0/__init__.py
kio/schema/add_offsets_to_txn/v0/request.py
kio/schema/add_offsets_to_txn/v0/response.py
kio/schema/add_offsets_to_txn/v1/__init__.py
kio/schema/add_offsets_to_txn/v1/request.py
kio/schema/add_offsets_to_txn/v1/response.py
kio/schema/add_offsets_to_txn/v2/__init__.py
kio/schema/add_offsets_to_txn/v2/request.py
kio/schema/add_offsets_to_txn/v2/response.py
kio/schema/add_offsets_to_txn/v3/__init__.py
kio/schema/add_offsets_to_txn/v3/request.py
kio/schema/add_offsets_to_txn/v3/response.py
kio/schema/add_offsets_to_txn/v4/__init__.py
kio/schema/add_offsets_to_txn/v4/request.py
kio/schema/add_offsets_to_txn/v4/response.py
kio/schema/add_partitions_to_txn/__init__.py
kio/schema/add_partitions_to_txn/v0/__init__.py
kio/schema/add_partitions_to_txn/v0/request.py
kio/schema/add_partitions_to_txn/v0/response.py
kio/schema/add_partitions_to_txn/v1/__init__.py
kio/schema/add_partitions_to_txn/v1/request.py
kio/schema/add_partitions_to_txn/v1/response.py
kio/schema/add_partitions_to_txn/v2/__init__.py
kio/schema/add_partitions_to_txn/v2/request.py
kio/schema/add_partitions_to_txn/v2/response.py
kio/schema/add_partitions_to_txn/v3/__init__.py
kio/schema/add_partitions_to_txn/v3/request.py
kio/schema/add_partitions_to_txn/v3/response.py
kio/schema/add_partitions_to_txn/v4/__init__.py
kio/schema/add_partitions_to_txn/v4/request.py
kio/schema/add_partitions_to_txn/v4/response.py
kio/schema/add_partitions_to_txn/v5/__init__.py
kio/schema/add_partitions_to_txn/v5/request.py
kio/schema/add_partitions_to_txn/v5/response.py
kio/schema/add_raft_voter/__init__.py
kio/schema/add_raft_voter/v0/__init__.py
kio/schema/add_raft_voter/v0/request.py
kio-0.4.0.dist-info/licenses/LICENSE
kio-0.4.0.dist-info/licenses/NOTICE
kio-0.4.0.dist-info/METADATA
kio-0.4.0.dist-info/WHEEL
kio-0.4.0.dist-info/top_level.txt
kio-0.4.0.dist-info/RECORD
