Metadata-Version: 2.4
Name: kio
Version: 0.4.0
Summary: Python data types for the Apache Kafka® Protocol.
Author-email: Anton Agestam <anton.agestam@aiven.io>
License-Expression: Apache-2.0
Project-URL: Source Repository, https://github.com/Aiven-Open/kio
Project-URL: Documentation, https://aiven-open.github.io/kio/
Project-URL: Bug Tracker, https://github.com/Aiven-Open/kio/issues
Classifier: Intended Audience :: Developers
Classifier: Operating System :: OS Independent
Classifier: Programming Language :: Python
Classifier: Programming Language :: Python :: 3
Classifier: Programming Language :: Python :: 3 :: Only
Classifier: Programming Language :: Python :: 3.11
Classifier: Programming Language :: Python :: 3.12
Classifier: Programming Language :: Python :: 3.13
Classifier: Typing :: Typed
Classifier: Topic :: Database
Requires-Python: >=3.11
License-File: LICENSE
License-File: NOTICE
Requires-Dist: typing-extensions>=4.6.0
Requires-Dist: crc32c>=2.3
Provides-Extra: test
Requires-Dist: pytest; extra == "test"
Requires-Dist: pytest-asyncio; extra == "test"
Requires-Dist: pytest-icdiff; extra == "test"
Requires-Dist: pytest-random-order; extra == "test"
Requires-Dist: hypothesis>=6.61.0; extra == "test"
Requires-Dist: coverage; extra == "test"
Provides-Extra: codegen
Requires-Dist: pydantic<2,>=1.10.4; extra == "codegen"
Requires-Dist: requests; extra == "codegen"
Requires-Dist: pre-commit; extra == "codegen"
Provides-Extra: all
Requires-Dist: kio[test]; extra == "all"
Requires-Dist: kio[codegen]; extra == "all"
Dynamic: license-file
